MANIFEST.in
README.md
requirements.txt
setup.py
R3con1z3r.egg-info/PKG-INFO
R3con1z3r.egg-info/SOURCES.txt
R3con1z3r.egg-info/dependency_links.txt
R3con1z3r.egg-info/entry_points.txt
R3con1z3r.egg-info/requires.txt
R3con1z3r.egg-info/top_level.txt
R3con1z3r.egg-info/zip-safe
r3con1z3r/__init__.py
r3con1z3r/cli.py
r3con1z3r/spin.py