Metadata-Version: 2.1
Name: R3con1z3r
Version: 1.0.6
Summary: R3con1z3r is a lightweight Web information gathering tool with an intuitive features written in python. it provides a powerful environment in which open source intelligence (OSINT) web-based footprinting can be conducted quickly and thoroughly.
Home-page: https://github.com/abdulgaphy/r3con1z3r
Author: AbdulGaphy
Author-email: 
License: MIT
Keywords: OSINT web reconnaisance traceroute footprinting DNS
Platform: UNKNOWN
Classifier: Programming Language :: Python
Classifier: License :: OSI Approved :: MIT License
Classifier: Operating System :: OS Independent
